{"note":"Don't delete this file! It's used internally to help with page regeneration.","tagline":"Distributed Asynchronous Hyperparameter Optimization in Python","google":"","name":"Hyperopt","body":"# What is Hyperopt?\r\n\r\n`hyperopt` is a Python library for optimizing over awkward\r\nsearch spaces with real-valued, discrete, and conditional\r\ndimensions.\r\n\r\n```python\r\n# define an objective function\r\ndef objective(args):\r\n    case, val = args\r\n    if case == 'case 1':\r\n        return val\r\n    else:\r\n        return val ** 2\r\n\r\n# define a search space\r\nfrom hyperopt import hp\r\nspace = hp.choice('a',\r\n    [\r\n        ('case 1', 1 + hp.lognormal('c1', 0, 1)),\r\n        ('case 2', hp.uniform('c2', -10, 10))\r\n    ])\r\n\r\n# minimize the objective over the space\r\nfrom hyperopt import fmin, tpe\r\nbest = fmin(objective, space, algo=tpe.suggest, max_evals=100)\r\nprint best\r\n# -> {'a': 1, 'c2': 0.01420615366247227}\r\n```\r\n\r\n# Algorithms\r\n\r\nCurrently two algorithms are implemented in hyperopt:\r\n\r\n* Random Search\r\n* Tree of Parzen Estimators (TPE)\r\n\r\nHyperopt has been designed to accommodate Bayesian optimization algorithms\r\nbased on Gaussian processes and regression trees, but these are not\r\ncurrently implemented.\r\n\r\nAll algorithms can be run either serially, or in parallel by communicating via [MongoDB](http://www.mongodb.org).\r\n\r\n\r\n# Installation\r\n\r\nCheck out the master version of hyperopt from github by typing e.g.\r\n\r\n    git clone https://github.com/jaberg/hyperopt.git\r\n\r\nand then install it by typing e.g.\r\n\r\n    (cd hyperopt && python setup.py install)\r\n\r\nFor more information see [Installation Notes](https://github.com/jaberg/hyperopt/wiki/Installation-Notes).\r\n\r\n# Testing\r\n\r\nRun the test suite with `py.test` or `nose`. I use nose myself:\r\n\r\n    (cd hyperopt && nosetests)\r\n\r\nAll tests should pass, or be skipped. Please file a github issue if you see errors or failures.\r\n\r\n# Documentation\r\n\r\n[Documentation is currently hosted on the wiki](https://github.com/jaberg/hyperopt/wiki/Home), but here are some quick links to the most relevant pages:\r\n\r\n* [Basic tutorial](https://github.com/jaberg/hyperopt/wiki/FMin)\r\n* [Installation notes](https://github.com/jaberg/hyperopt/wiki/Installation-Notes)\r\n* [Using mongodb](https://github.com/jaberg/hyperopt/wiki/Parallelizing-Evaluations-During-Search-via-MongoDB)\r\n\r\n# Examples\r\n\r\nSee [projects using hyperopt](https://github.com/jaberg/hyperopt/wiki/Hyperopt-in-Other-Projects) on the wiki."}